AUTHOR
COPYING
MANIFEST.in
README.rst
setup.py
switching/__init__.py
switching/defs.py
switching/utils.py
switching.egg-info/PKG-INFO
switching.egg-info/SOURCES.txt
switching.egg-info/dependency_links.txt
switching.egg-info/pbr.json
switching.egg-info/requires.txt
switching.egg-info/top_level.txt
switching/data/AceptacionAnulacion.xsd
switching/data/AceptacionAportacionLectura.xsd
switching/data/AceptacionBajaEnergia.xsd
switching/data/AceptacionCambiodeComercializadoraConCambios.xsd
switching/data/AceptacionCambiodeComercializadoraSinCambios.xsd
switching/data/AceptacionModificacionDeATR.xsd
switching/data/AceptacionPasoMRAMLConCambiosRestoTarifa.xsd
switching/data/AceptacionReclamacion.xsd
switching/data/ActivacionCambiodeComercializadoraConCambios.xsd
switching/data/ActivacionCambiodeComercializadoraSinCambios.xsd
switching/data/ActivacionModificacionDeATR.xsd
switching/data/ActivacionPasoMRAMLConCambiosRestoTarifas.xsd
switching/data/AnulacionSolicitud.xsd
switching/data/BajaEnergia.xsd
switching/data/CambiodeComercializadoraConCambios.xsd
switching/data/CambiodeComercializadoraSinCambios.xsd
switching/data/CierreReclamacion.xsd
switching/data/EnvioInformacionReclamacion.xsd
switching/data/Facturacion.xsd
switching/data/IncidenciasATRDistribuidoras.xsd
switching/data/MensajeAportacionLectura.xsd
switching/data/ModificacionDeATR.xsd
switching/data/NotificacionBajaEnergia.xsd
switching/data/NotificacionCambiosATRDesdeDistribuidor.xsd
switching/data/NotificacionComercializadoraSaliente.xsd
switching/data/PasoMRAMLConCambiosRestoTarifas.xsd
switching/data/PeticionInformacionAdicionalReclamacion.xsd
switching/data/RechazoATRDistribuidoras.xsd
switching/data/RechazoAnulacion.xsd
switching/data/RechazoAportacionLectura.xsd
switching/data/RechazoReclamacion.xsd
switching/data/ReclamacionPeticion.xsd
switching/data/SaldoLecturasFacturacion.xsd
switching/data/TipoCabecera.xsd
switching/data/TipoCabeceraReclamacion.xsd
switching/data/TipoMensajeAA3.xsd
switching/data/TipoMensajeAB1.xsd
switching/data/TipoMensajeAC1.xsd
switching/data/TipoMensajeAC2.xsd
switching/data/TipoMensajeAM1.xsd
switching/data/TipoMensajeAN.xsd
switching/data/TipoMensajeBN.xsd
