Metadata-Version: 1.1
Name: switching
Version: 2.12.1
Summary: Llibreria de switching
Home-page: http://www.gisce.net
Author: GISCE Enginyeria
Author-email: devel@gisce.net
License: General Public Licence 2
Platform: UNKNOWN
Provides: switching
